ssw/__init__.py
ssw/libssw.cpython-36m-darwin.so
ssw/ssw.c
ssw/ssw.h
ssw/ssw_wrap.py
svviz/__init__.py
svviz/align_proc.py
svviz/alignment.py
svviz/alignproc.py
svviz/annotations.py
svviz/app.py
svviz/commandline.py
svviz/datahub.py
svviz/debug.py
svviz/demo.py
svviz/disambiguate.py
svviz/dotplots.py
svviz/export.py
svviz/flanking.py
svviz/genomesource.py
svviz/gff.py
svviz/insertsizes.py
svviz/kde.py
svviz/misc.py
svviz/multiprocessor.py
svviz/pairfinder.py
svviz/plotting.py
svviz/remap.py
svviz/rendertest.py
svviz/summarystats.py
svviz/svg.py
svviz/tabix.py
svviz/testCounts.py
svviz/testDemos.py
svviz/testIssues.py
svviz/track.py
svviz/utilities.py
svviz/variants.py
svviz/vcf.py
svviz/web.py
svviz/static/bootstrap.css
svviz/static/bootstrap.js
svviz/static/installPDFExport.html
svviz/static/interface.js
svviz/static/jquery-ui.css
svviz/static/jquery-ui.js
svviz/static/jquery.js
svviz/static/jquery.mousewheel.js
svviz/static/main.css
svviz/static/svgscroller.js
svviz/templates/index.html
svviz-1.6.2.dist-info/DESCRIPTION.rst
svviz-1.6.2.dist-info/METADATA
svviz-1.6.2.dist-info/RECORD
svviz-1.6.2.dist-info/WHEEL
svviz-1.6.2.dist-info/entry_points.txt
svviz-1.6.2.dist-info/metadata.json
svviz-1.6.2.dist-info/pbr.json
svviz-1.6.2.dist-info/top_level.txt
