Metadata-Version: 2.0
Name: svviz
Version: 1.6.2
Summary: A read visualizer for structural variants
Home-page: https://github.com/svviz/svviz
Author: Noah Spies
Author-email: nspies@stanford.edu
License: MIT
Keywords: bioinformatics,structural variants,sequence analysis
Platform: UNKNOWN
Classifier: Development Status :: 5 - Production/Stable
Classifier: License :: OSI Approved :: MIT License
Classifier: Intended Audience :: Science/Research
Classifier: Natural Language :: English
Classifier: Operating System :: Unix
Classifier: Programming Language :: Python :: 2.7
Classifier: Programming Language :: Python :: 2.6
Classifier: Topic :: Scientific/Engineering :: Bio-Informatics
Classifier: Topic :: Scientific/Engineering :: Visualization
Requires-Dist: flask
Requires-Dist: numpy
Requires-Dist: pyfaidx
Requires-Dist: pysam (>=0.10)
Requires-Dist: requests
Requires-Dist: six
